llama_index/readers/papers/__init__.py
llama_index/readers/papers/arxiv/__init__.py
llama_index/readers/papers/arxiv/base.py
llama_index/readers/papers/pubmed/__init__.py
llama_index/readers/papers/pubmed/base.py
llama_index_readers_papers-0.4.1.dist-info/METADATA
llama_index_readers_papers-0.4.1.dist-info/WHEEL
llama_index_readers_papers-0.4.1.dist-info/licenses/LICENSE
llama_index_readers_papers-0.4.1.dist-info/RECORD
