Metadata-Version: 2.4
Name: llama-index-readers-papers
Version: 0.4.1
Summary: llama-index readers papers integration
Author-email: Your Name <you@example.com>
Maintainer: thejessezhang
License-Expression: MIT
License-File: LICENSE
Requires-Python: <4.0,>=3.9
Requires-Dist: arxiv<3,>=2.1.0
Requires-Dist: defusedxml<0.8,>=0.7.1
Requires-Dist: llama-index-core<0.15,>=0.13.0
